vision_converter/__init__.py
vision_converter/cli/__init__.py
vision_converter/cli/main.py
vision_converter/converters/__init__.py
vision_converter/converters/coco_converter.py
vision_converter/converters/createml_converter.py
vision_converter/converters/dataset_converter.py
vision_converter/converters/labelme_converter.py
vision_converter/converters/pascal_voc_converter.py
vision_converter/converters/tensorflow_csv_converter.py
vision_converter/converters/vgg_converter.py
vision_converter/converters/yolo_converter.py
vision_converter/formats/__init__.py
vision_converter/formats/base.py
vision_converter/formats/coco.py
vision_converter/formats/createml.py
vision_converter/formats/labelme.py
vision_converter/formats/neutral_format.py
vision_converter/formats/pascal_voc.py
vision_converter/formats/tensorflow_csv.py
vision_converter/formats/vgg.py
vision_converter/formats/yolo.py
vision_converter/utils/__init__.py
vision_converter/utils/bbox_utils.py
vision_converter/utils/file_utils.py
vision_converter-0.1.0.dist-info/licenses/LICENSE
vision_converter-0.1.0.dist-info/METADATA
vision_converter-0.1.0.dist-info/WHEEL
vision_converter-0.1.0.dist-info/entry_points.txt
vision_converter-0.1.0.dist-info/top_level.txt
vision_converter-0.1.0.dist-info/RECORD
