Metadata-Version: 2.4
Name: vision-converter
Version: 0.1.0
Summary: This project consist of a library and a CLI for converting datasets between annotation formats.
Author: Guillermo Cousido Martínez
Author-email: Guillermo Cousido Martínez <guillermo.cousido@gmail.com>
License-Expression: MIT
Project-URL: Homepage, https://github.com/GCousido/VisionConverter
Project-URL: Documentation, https://github.com/GCousido/VisionConverter#readme
Project-URL: Repository, https://github.com/GCousido/VisionConverter
Project-URL: Issues, https://github.com/GCousido/VisionConverter/issues
Project-URL: Changelog, https://github.com/GCousido/VisionConverter/releases
Keywords: dataset,converter,computer vision,cli,yolo,coco,pascal voc
Classifier: Programming Language :: Python :: 3
Classifier: Programming Language :: Python :: 3.12
Classifier: Operating System :: OS Independent
Classifier: Intended Audience :: Developers
Classifier: Topic :: Software Development :: Libraries :: Python Modules
Requires-Python: >=3.12
License-File: LICENSE
Requires-Dist: click>=8.1.8
Requires-Dist: pillow>=11.2.1
Provides-Extra: dev
Requires-Dist: pytest>=8.3.5; extra == "dev"
Requires-Dist: pytest-mock>=3.14.0; extra == "dev"
Dynamic: author
Dynamic: license-file
Dynamic: requires-python
